ProtoMsg/ControlIn_pb2.py
ProtoMsg/ControlOut_pb2.py
ProtoMsg/KafkaMessage_pb2.py
ProtoMsg/SegmentCommon_pb2.py
ProtoMsg/SegmentIn_pb2.py
ProtoMsg/SegmentOut_pb2.py
ProtoMsg/__init__.py
ProtoMsg/version.py
ProtoMsg-1.0.3.dist-info/METADATA
ProtoMsg-1.0.3.dist-info/WHEEL
ProtoMsg-1.0.3.dist-info/top_level.txt
ProtoMsg-1.0.3.dist-info/RECORD
