Metadata-Version: 2.1
Name: ProtoMsg
Version: 1.0.3
Summary: scu-yang-proto-msg
Author: loorr
Author-email: zjianfa@foxmail.com
License: apache 3.0
Requires: protobuf
